bootstrap.py
buildout.cfg
setup.py
collective/__init__.py
collective.sectionsubskin.egg-info/PKG-INFO
collective.sectionsubskin.egg-info/SOURCES.txt
collective.sectionsubskin.egg-info/dependency_links.txt
collective.sectionsubskin.egg-info/entry_points.txt
collective.sectionsubskin.egg-info/namespace_packages.txt
collective.sectionsubskin.egg-info/not-zip-safe
collective.sectionsubskin.egg-info/requires.txt
collective.sectionsubskin.egg-info/top_level.txt
collective/sectionsubskin/README.txt
collective/sectionsubskin/__init__.py
collective/sectionsubskin/apply.py
collective/sectionsubskin/configure.zcml
collective/sectionsubskin/definition.py
collective/sectionsubskin/interfaces.py
collective/sectionsubskin/test_support.py
collective/sectionsubskin/test_support.zcml
collective/sectionsubskin/tests.py
collective/sectionsubskin/traverser.py
collective/sectionsubskin/browser/__init__.py
collective/sectionsubskin/browser/subskin.py
docs/HISTORY.txt
docs/INSTALL.txt
docs/LICENSE.GPL
docs/LICENSE.txt
var/README.txt
