Metadata-Version: 1.0
Name: collective.sectionsubskin
Version: 0.2
Summary: Apply a marker interface to a request to code for special presentation of a subsection.
Home-page: http://code.liberalyouth.org/basket/collective.sectionsubskin
Author: Matthew Wilkes
Author-email: matthew.wilkes@circulartriangle.eu
License: GPL
Platform: UNKNOWN
Classifier: Framework :: Plone
Classifier: Programming Language :: Python
Classifier: Topic :: Software Development :: Libraries :: Python Modules
